{"lastUsed":1656940698607,"path":"C:\/Users\/QA\/Desktop\/QAJava","projectCount":1,"recentFiles":[{"path":"\/SpringStarter\/src\/main\/java\/com\/qa\/may","parentWorkspace":"C:\/Users\/QA\/Desktop\/QAJava","name":"HelloController.java","lastModified":1656940698608,"locationURI":"file:\/C:\/Users\/QA\/Desktop\/QAJava\/SpringStarter\/src\/main\/java\/com\/qa\/may\/HelloController.java"},{"path":"\/SpringStarter\/src\/main\/java\/com\/qa\/may","parentWorkspace":"C:\/Users\/QA\/Desktop\/QAJava","name":"Person.java","lastModified":1656940203856,"locationURI":"file:\/C:\/Users\/QA\/Desktop\/QAJava\/SpringStarter\/src\/main\/java\/com\/qa\/may\/Person.java"},{"path":"\/SpringStarter\/src\/main\/java\/com\/qa\/may","parentWorkspace":"C:\/Users\/QA\/Desktop\/QAJava","name":"SpringStarterApplication.java","lastModified":1656938587510,"locationURI":"file:\/C:\/Users\/QA\/Desktop\/QAJava\/SpringStarter\/src\/main\/java\/com\/qa\/may\/SpringStarterApplication.java"}]}