{"lastUsed":1657117111327,"path":"C:\/Users\/QA\/Desktop\/QAJava","projectCount":3,"recentFiles":[{"path":"\/SpringStarter\/src\/main\/java\/com\/qa\/may\/service","parentWorkspace":"C:\/Users\/QA\/Desktop\/QAJava","name":"CarServiceList.java","lastModified":1657102330338,"locationURI":"file:\/C:\/Users\/QA\/Desktop\/QAJava\/SpringStarter\/src\/main\/java\/com\/qa\/may\/service\/CarServiceList.java"},{"path":"\/SpringStarter\/src\/main\/java\/com\/qa\/may\/entity","parentWorkspace":"C:\/Users\/QA\/Desktop\/QAJava","name":"Car.java","lastModified":1657106135194,"locationURI":"file:\/C:\/Users\/QA\/Desktop\/QAJava\/SpringStarter\/src\/main\/java\/com\/qa\/may\/entity\/Car.java"},{"path":"\/SpringStarter\/src\/main\/java\/com\/qa\/may","parentWorkspace":"C:\/Users\/QA\/Desktop\/QAJava","name":"HelloController.java","lastModified":1656947728142,"locationURI":"file:\/C:\/Users\/QA\/Desktop\/QAJava\/SpringStarter\/src\/main\/java\/com\/qa\/may\/HelloController.java"},{"path":"\/SpringStarter\/src\/main\/resources","parentWorkspace":"C:\/Users\/QA\/Desktop\/QAJava","name":"application.properties","lastModified":1657104313282,"locationURI":"file:\/C:\/Users\/QA\/Desktop\/QAJava\/SpringStarter\/src\/main\/resources\/application.properties"},{"path":"\/SpringStarter\/src\/test\/java\/com\/qa\/may\/rest","parentWorkspace":"C:\/Users\/QA\/Desktop\/QAJava","name":"CarControllerTest.java","lastModified":1657117111667,"locationURI":"file:\/C:\/Users\/QA\/Desktop\/QAJava\/SpringStarter\/src\/test\/java\/com\/qa\/may\/rest\/CarControllerTest.java"},{"path":"\/SpringStarter\/src\/main\/java\/com\/qa\/may\/rest","parentWorkspace":"C:\/Users\/QA\/Desktop\/QAJava","name":"CarController.java","lastModified":1657104197395,"locationURI":"file:\/C:\/Users\/QA\/Desktop\/QAJava\/SpringStarter\/src\/main\/java\/com\/qa\/may\/rest\/CarController.java"},{"path":"\/SpringStarter\/src\/main\/java\/com\/qa\/may\/service","parentWorkspace":"C:\/Users\/QA\/Desktop\/QAJava","name":"CarServiceDB.java","lastModified":1657106135675,"locationURI":"file:\/C:\/Users\/QA\/Desktop\/QAJava\/SpringStarter\/src\/main\/java\/com\/qa\/may\/service\/CarServiceDB.java"},{"path":"\/SpringStarter\/src\/main\/java\/com\/qa\/may","parentWorkspace":"C:\/Users\/QA\/Desktop\/QAJava","name":"Person.java","lastModified":1656940203856,"locationURI":"file:\/C:\/Users\/QA\/Desktop\/QAJava\/SpringStarter\/src\/main\/java\/com\/qa\/may\/Person.java"},{"path":"\/SpringStarter\/src\/main\/java\/com\/qa\/may","parentWorkspace":"C:\/Users\/QA\/Desktop\/QAJava","name":"SpringStarterApplication.java","lastModified":1656938587510,"locationURI":"file:\/C:\/Users\/QA\/Desktop\/QAJava\/SpringStarter\/src\/main\/java\/com\/qa\/may\/SpringStarterApplication.java"},{"path":"\/SpringStarter\/src\/main\/java\/com\/qa\/may\/repo","parentWorkspace":"C:\/Users\/QA\/Desktop\/QAJava","name":"CarRepo.java","lastModified":1657104435785,"locationURI":"file:\/C:\/Users\/QA\/Desktop\/QAJava\/SpringStarter\/src\/main\/java\/com\/qa\/may\/repo\/CarRepo.java"},{"path":"\/SpringStarter\/src\/main\/java\/com\/qa\/may\/service","parentWorkspace":"C:\/Users\/QA\/Desktop\/QAJava","name":"CarService.java","lastModified":1657100521697,"locationURI":"file:\/C:\/Users\/QA\/Desktop\/QAJava\/SpringStarter\/src\/main\/java\/com\/qa\/may\/service\/CarService.java"}]}